datatypes_date_time/__init__.py
datatypes_date_time/date_range.py
datatypes_date_time/time.py
datatypes_date_time/time_range.py
datatypes_date_time/timex.py
datatypes_date_time/timex_constants.py
datatypes_date_time/timex_convert.py
datatypes_date_time/timex_date_helpers.py
datatypes_date_time/timex_format.py
datatypes_date_time/timex_helpers.py
datatypes_date_time/timex_inference.py
datatypes_date_time/timex_parsing.py
datatypes_date_time/timex_range.py
datatypes_date_time/timex_regex.py
datatypes_date_time/timex_relative_convert.py
datatypes_date_time-1.0.0a2.dist-info/METADATA
datatypes_date_time-1.0.0a2.dist-info/WHEEL
datatypes_date_time-1.0.0a2.dist-info/top_level.txt
datatypes_date_time-1.0.0a2.dist-info/RECORD
